{
  "indexes": [
    {
      "collectionGroup": "periods",
      "queryScope": "COLLECTION",
      "fields": [
        {
          "fieldPath": "closedAt",
          "order": "ASCENDING"
        },
        {
          "fieldPath": "startAt",
          "order": "DESCENDING"
        }
      ]
    },
    {
      "collectionGroup": "spending",
      "queryScope": "COLLECTION",
      "fields": [
        {
          "fieldPath": "periodId",
          "order": "ASCENDING"
        },
        {
          "fieldPath": "date",
          "order": "DESCENDING"
        }
      ]
    }
  ],
  "fieldOverrides": []
}
